icantech/__init__.py
icantech/__init__.pyi
icantech/replit/__init__.py
icantech/replit/__init__.pyi
icantech/replit/observe.py
icantech/replit/observe.pyi
icantech/replit/unittest/__init__.py
icantech/replit/unittest/__init__.pyi
icantech-1.0.4.dist-info/LICENSE
icantech-1.0.4.dist-info/METADATA
icantech-1.0.4.dist-info/WHEEL
icantech-1.0.4.dist-info/top_level.txt
icantech-1.0.4.dist-info/RECORD
